sitq/__init__.py
sitq/_mips.py
sitq/_sitq.py
sitq-0.1.3.dist-info/LICENSE
sitq-0.1.3.dist-info/METADATA
sitq-0.1.3.dist-info/WHEEL
sitq-0.1.3.dist-info/top_level.txt
sitq-0.1.3.dist-info/RECORD
