Metadata-Version: 2.1
Name: sitq
Version: 0.1.3
Summary: Learning to Hash for Maximum Inner Product Search
Home-page: https://github.com/shiroyagicorp/sitq
Author: Kazuaki Tanida
Author-email: UNKNOWN
License: MIT
Keywords: MIPS,LSH,ITQ,Maximum Inner Product Search
Platform: UNKNOWN
Classifier: Programming Language :: Python :: 3
Classifier: License :: OSI Approved :: MIT License
Requires-Dist: numpy
Requires-Dist: pqkmeans
